crowd_counting/__init__.py
crowd_counting/models/__init__.py
crowd_counting/models/edet.py
crowd_counting/models/sanet.py
crowd_counting/utils/__init__.py
crowd_counting/utils/tools.py
face_recognition/__init__.py
face_recognition/models/__init__.py
face_recognition/models/arcnet.py
face_recognition/models/retina.py
face_recognition/utils/__init__.py
face_recognition/utils/tools.py
imutils/__init__.py
imutils/convenience.py
imutils/logger.py
imutils/meta.py
imutils/video/__init__.py
imutils/video/count_frames.py
imutils/video/filevideostream.py
imutils/video/fps.py
imutils/video/pivideostream.py
imutils/video/videostream.py
imutils/video/webcamvideostream.py
license_recognition/__init__.py
license_recognition/models/__init__.py
license_recognition/models/ocr.py
license_recognition/models/wpod.py
license_recognition/utils/__init__.py
license_recognition/utils/label.py
license_recognition/utils/tools.py
orientation_recognition/__init__.py
orientation_recognition/models/__init__.py
orientation_recognition/models/resnet34.py
orientation_recognition/utils/__init__.py
orientation_recognition/utils/tools.py
greenlab_library-0.1.5.4.dist-info/LICENSE
greenlab_library-0.1.5.4.dist-info/METADATA
greenlab_library-0.1.5.4.dist-info/WHEEL
greenlab_library-0.1.5.4.dist-info/top_level.txt
greenlab_library-0.1.5.4.dist-info/RECORD
