Metadata-Version: 2.1
Name: greenlab-library
Version: 0.1.5.4
Summary: HungLV package
Home-page: https://gitlab.com/greenlabs/greenlab_libraries
Author: Hung LV
Author-email: hunglv@greenglobal.vn
License: MIT
Platform: UNKNOWN
Classifier: Programming Language :: Python :: 3
Classifier: License :: OSI Approved :: MIT License
Classifier: Operating System :: OS Independent
Requires-Python: >=3.6
